LICENSE
README.md
setup.py
inspeq/__init__.py
inspeq/client.py
inspeq/config_file.json
inspeqai.egg-info/PKG-INFO
inspeqai.egg-info/SOURCES.txt
inspeqai.egg-info/dependency_links.txt
inspeqai.egg-info/requires.txt
inspeqai.egg-info/top_level.txt