Metadata-Version: 2.1
Name: inspeqai
Version: 1.0.30
Summary: Inspeq AI Python SDK
Home-page: UNKNOWN
Author: Inspeq
Author-email: support@inspeq.ai
License: Apache 2.0
Project-URL: Documentation, https://docs.inspeq.ai
Project-URL: Source, https://github.com/inspeq/inspeq-py-sdk
Platform: UNKNOWN
Requires-Python: >=3.10
License-File: LICENSE
